stravacz_mcp-1.0.0.dist-info/licenses/LICENSE
stravacz_mcp_server/__init__.py
stravacz_mcp_server/server.py
stravacz_mcp_server/server_http.py
stravacz_mcp_server/strava_client.py
stravacz_mcp-1.0.0.dist-info/METADATA
stravacz_mcp-1.0.0.dist-info/WHEEL
stravacz_mcp-1.0.0.dist-info/entry_points.txt
stravacz_mcp-1.0.0.dist-info/top_level.txt
stravacz_mcp-1.0.0.dist-info/RECORD
