Metadata-Version: 2.4
Name: stravacz-mcp
Version: 1.0.0
Summary: Neoficiální Model Context Protocol server pro strava.cz - český systém objednávání stravy v jídelnách
Author-email: mirecekd <mirecekd@gmail.com>
License: MIT
Project-URL: Homepage, https://github.com/mirecekd/stravacz-mcp
Project-URL: Bug Reports, https://github.com/mirecekd/stravacz-mcp/issues
Project-URL: Source, https://github.com/mirecekd/stravacz-mcp
Keywords: mcp,strava.cz,canteen,jidelna,api
Classifier: Development Status :: 4 - Beta
Classifier: Intended Audience :: Developers
Classifier: License :: OSI Approved :: MIT License
Classifier: Programming Language :: Python :: 3
Classifier: Programming Language :: Python :: 3.8
Classifier: Programming Language :: Python :: 3.9
Classifier: Programming Language :: Python :: 3.10
Classifier: Programming Language :: Python :: 3.11
Classifier: Programming Language :: Python :: 3.12
Requires-Python: >=3.8
License-File: LICENSE
Requires-Dist: strava-cz>=0.1.3
Requires-Dist: fastmcp>=0.9.0
Requires-Dist: aiohttp>=3.8.0
Requires-Dist: asyncio
Provides-Extra: dev
Requires-Dist: pytest>=7.0.0; extra == "dev"
Requires-Dist: pytest-asyncio>=0.21.0; extra == "dev"
Requires-Dist: black>=22.0.0; extra == "dev"
Requires-Dist: flake8>=4.0.0; extra == "dev"
Requires-Dist: mypy>=0.991; extra == "dev"
Dynamic: license-file
